pytelligence/__init__.py
pytelligence/dev_tools.py
pytelligence/feat_analysis.py
pytelligence/modelling/__init__.py
pytelligence/modelling/_compare_algorithms.py
pytelligence/modelling/_export_model.py
pytelligence/modelling/_internals/__init__.py
pytelligence/modelling/_internals/_models.py
pytelligence/modelling/_internals/_prep_pipeline.py
pytelligence/modelling/_internals/_setup.py
pytelligence/modelling/_internals/_utils.py
pytelligence/modelling/_prepare_data.py
pytelligence/modelling/_reduce_feature_space.py
pytelligence/modelling/_settings.py
pytelligence/modelling/_train_model.py
pytelligence/modelling/_tune_hyperparams.py
pytelligence-0.2.2.dist-info/WHEEL
pytelligence-0.2.2.dist-info/METADATA
pytelligence-0.2.2.dist-info/RECORD
